bin/__init__.py
bin/align.py
bin/main.py
bin/preprocess.py
bin/qc_plot_functions.py
bin/utils.py
bin/visualise.py
scGP-0.1.9.dist-info/LICENSE
scGP-0.1.9.dist-info/METADATA
scGP-0.1.9.dist-info/WHEEL
scGP-0.1.9.dist-info/entry_points.txt
scGP-0.1.9.dist-info/top_level.txt
scGP-0.1.9.dist-info/RECORD
