Metadata-Version: 2.1
Name: scGP
Version: 0.1.9
Summary: A package for simple scRNAseq analysis
Home-page: https://github.com/gpomeranz/scGP
Author: Gideon Pomeranz
Author-email: ucbtpom@ucl.ac.uk
License: UNKNOWN
Platform: UNKNOWN
Classifier: Programming Language :: Python :: 3
Classifier: License :: OSI Approved :: MIT License
Classifier: Operating System :: OS Independent
Requires-Python: >=3.6
Requires-Dist: anndata (>=0.7.4)
Requires-Dist: scanpy
Requires-Dist: numpy
Requires-Dist: harmony-pytorch
Requires-Dist: matplotlib
